{
    "k": 7,
    "solution": "U2;R3;L3;F1;U3;D1;L2",
    "total_prep_time": "0:00:03.334821",
    "total_solve_time": "0:00:00.372914",
    "total_time": "0:00:03.707735",
    "prep_times": {
        "0": "0:00:00.009810",
        "1": "0:00:00.112006",
        "2": "0:00:00.224288",
        "3": "0:00:00.341494",
        "4": "0:00:00.459511",
        "5": "0:00:00.602890",
        "6": "0:00:00.723945",
        "7": "0:00:00.860877"
    },
    "solve_times": {
        "0": "0:00:00.000820",
        "1": "0:00:00.000632",
        "2": "0:00:00.001132",
        "3": "0:00:00.000703",
        "4": "0:00:00.016774",
        "5": "0:00:00.072868",
        "6": "0:00:00.108661",
        "7": "0:00:00.171324"
    }
}